django_field_cryptography/__init__.py
django_field_cryptography/fields.py
django_field_cryptography/tests/__init__.py
django_field_cryptography/tests/factories.py
django_field_cryptography/tests/models.py
django_field_cryptography/tests/run.py
django_field_cryptography/tests/test_fields.py
django_field_cryptography-1.0.0.dist-info/DESCRIPTION.rst
django_field_cryptography-1.0.0.dist-info/METADATA
django_field_cryptography-1.0.0.dist-info/metadata.json
django_field_cryptography-1.0.0.dist-info/RECORD
django_field_cryptography-1.0.0.dist-info/top_level.txt
django_field_cryptography-1.0.0.dist-info/WHEEL
