Metadata-Version: 2.0
Name: django-field-cryptography
Version: 1.0.0
Summary: An encrypted field for Django.
Home-page: https://github.com/incuna/django-field-cryptography
Author: Incuna Ltd
Author-email: admin@incuna.com
License: BSD
Platform: UNKNOWN
Requires-Dist: cryptography (>=0.6,<0.7)
